{
  "guitars": [
    {
      "title": "メーカー不明 Melody Maker メロディメーカー エレキギター 中古 S9956905",
      "price": "33,000 иена(иен) (US$241,89)",
      "image": "https://cdn.buyee.jp/images/common/spacer.gif",
      "url": "https://buyee.jp/item/jdirectitems/auction/m1183855608",
      "source": "buyee",
      "condition": "Незначительные повреждения/грязь",
      "endDate": "09.05.2025 22:47",
      "timeRemaining": "Осталось: 1 дн. 22 ч. 43 мин."
    },
    {
      "title": "ESP ハードケース エレキギター用 中古 T9976568",
      "price": "26,400 иена(иен) (US$193,52)",
      "image": "https://cdn.buyee.jp/images/common/spacer.gif",
      "url": "https://buyee.jp/item/jdirectitems/auction/l1183841498",
      "source": "buyee",
      "condition": "Незначительные повреждения/грязь",
      "endDate": "09.05.2025 22:42",
      "timeRemaining": "Осталось: 1 дн. 22 ч. 38 мин."
    },
    {
      "title": "Burns LONDON SONIC Custom Elite Series エレキ ギター ブルー バーンズ ロンドン 中古 良好 C9968302",
      "price": "54,560 иена(иен) (US$399,93)",
      "image": "https://cdn.buyee.jp/images/common/spacer.gif",
      "url": "https://buyee.jp/item/jdirectitems/auction/v1183853726",
      "source": "buyee",
      "condition": "Нет видимых повреждений/грязи",
      "endDate": "09.05.2025 22:59",
      "timeRemaining": "Осталось: 1 дн. 22 ч. 55 мин."
    },
    {
      "title": "YAMAHA ヤマハ SF500 Super Flighter スーパーフライター エレキギター 中古 W9981016",
      "price": "37,400 иена(иен) (US$274,15)",
      "image": "https://cdn.buyee.jp/images/common/spacer.gif",
      "url": "https://buyee.jp/item/jdirectitems/auction/m1183597839",
      "source": "buyee",
      "condition": "Незначительные повреждения/грязь",
      "endDate": "08.05.2025 22:12",
      "timeRemaining": "Осталось: 22 ч. 8 мин."
    },
    {
      "title": "YAMAHA PAC612VIIFM エレキギター 6弦 ギター ヤマハ 楽器 良好 W9908547",
      "price": "49,500 иена(иен) (US$362,84)",
      "image": "https://cdn.buyee.jp/images/common/spacer.gif",
      "url": "https://buyee.jp/item/jdirectitems/auction/d1183442162",
      "source": "buyee",
      "condition": "Нет видимых повреждений/грязи",
      "endDate": "09.05.2025 22:47",
      "timeRemaining": "Осталось: 1 дн. 22 ч. 43 мин."
    },
    {
      "title": "EVH Wolfgang Special Ebony Stealth Black ウルフギャング スペシャル ステルスブラック エレキギター 中古 良好T9958187",
      "price": "102,960 иена(иен) (US$754,70)",
      "image": "https://cdn.buyee.jp/images/common/spacer.gif",
      "url": "https://buyee.jp/item/jdirectitems/auction/u1183941469",
      "source": "buyee",
      "condition": "Нет видимых повреждений/грязи",
      "endDate": "09.05.2025 22:07",
      "timeRemaining": "Осталось: 1 дн. 22 ч. 3 мин."
    },
    {
      "title": "strandberg＊ BODEN J6 エレキギター 6弦 ヘッドレス ストランドバーグ 中古 良好 C9992112",
      "price": "411,510 иена(иен) (US$3 016,37)",
      "image": "https://cdn.buyee.jp/images/common/spacer.gif",
      "url": "https://buyee.jp/item/jdirectitems/auction/d1183787751",
      "source": "buyee",
      "condition": "Нет видимых повреждений/грязи",
      "endDate": "08.05.2025 22:34",
      "timeRemaining": "Осталось: 22 ч. 30 мин."
    },
    {
      "title": "PRS John Mayer Signature Model JM SILVER SKY J3 Horizon ポールリードスミス ジョンメイヤー シルバースカイ 中古 美品T9958071",
      "price": "260,260 иена(иен) (US$1 907,71)",
      "image": "https://cdn.buyee.jp/images/common/spacer.gif",
      "url": "https://buyee.jp/item/jdirectitems/auction/n1183911678",
      "source": "buyee",
      "condition": "Практически не б/у",
      "endDate": "09.05.2025 22:58",
      "timeRemaining": "Осталось: 1 дн. 22 ч. 54 мин."
    },
    {
      "title": "Gibson ギブソン USA 2014 Les Paul special TV yellow エレキ ギター 良好T9985271",
      "price": "169,400 иена(иен) (US$1 241,71)",
      "image": "https://cdn.buyee.jp/images/common/spacer.gif",
      "url": "https://buyee.jp/item/jdirectitems/auction/o1183889651",
      "source": "buyee",
      "condition": "Нет видимых повреждений/грязи",
      "endDate": "09.05.2025 22:46",
      "timeRemaining": "Осталось: 1 дн. 22 ч. 42 мин."
    },
    {
      "title": "SCHECTER DIAMOND SERIES OMEN EXTREME-6 エレキ ギター シェクター 中古 S9989382",
      "price": "15,840 иена(иен) (US$116,11)",
      "image": "https://cdn.buyee.jp/images/common/spacer.gif",
      "url": "https://buyee.jp/item/jdirectitems/auction/c1183619497",
      "source": "buyee",
      "condition": "Незначительные повреждения/грязь",
      "endDate": "11.05.2025 22:04",
      "timeRemaining": "Осталось: 3 дн. 22 ч. 0 мин."
    },
    {
      "title": "☆エピフォン フライングV エレキギター 黒 15032300269 試奏未確認",
      "price": "33,000 иена(иен) (US$241,89)",
      "image": "https://cdn.buyee.jp/images/common/spacer.gif",
      "url": "https://buyee.jp/item/jdirectitems/auction/x1183771674",
      "source": "buyee",
      "condition": "Незначительные повреждения/грязь",
      "endDate": "11.05.2025 22:52",
      "timeRemaining": "Осталось: 3 дн. 22 ч. 48 мин."
    },
    {
      "title": "Rockoon RF-37 エレキギター",
      "price": "28,600 иена(иен) (US$209,64)",
      "image": "https://cdn.buyee.jp/images/common/spacer.gif",
      "url": "https://buyee.jp/item/jdirectitems/auction/e1179702056",
      "source": "buyee",
      "condition": "Незначительные повреждения/грязь",
      "endDate": "08.05.2025 22:14",
      "timeRemaining": "Осталось: 22 ч. 9 мин."
    },
    {
      "title": "Fender Japan ST-62 2004-2006年頃 エレキギター ダイナ ストラトキャスター フェンダージャパン 中古 W9975906",
      "price": "55,000 иена(иен) (US$403,15)",
      "image": "https://cdn.buyee.jp/images/common/spacer.gif",
      "url": "https://buyee.jp/item/jdirectitems/auction/x1183495609",
      "source": "buyee",
      "condition": "Незначительные повреждения/грязь",
      "endDate": "08.05.2025 22:46",
      "timeRemaining": "Осталось: 22 ч. 42 мин."
    },
    {
      "title": "大特価 動作品【管理番号G】RYOGA HORNET／LE エレキギター",
      "price": "29,263 иена(иен) (US$214,50)",
      "image": "https://cdn.buyee.jp/images/common/spacer.gif",
      "url": "https://buyee.jp/item/jdirectitems/auction/s1166342652",
      "source": "buyee",
      "condition": "Незначительные повреждения/грязь",
      "endDate": "08.05.2025 22:40",
      "timeRemaining": "Осталось: 22 ч. 36 мин."
    },
    {
      "title": "RYOGA HORNET LE エレキギター ソフトケース付き",
      "price": "22,473 иена(иен) (US$164,73)",
      "image": "https://cdn.buyee.jp/images/common/spacer.gif",
      "url": "https://buyee.jp/item/jdirectitems/auction/d1158565598",
      "source": "buyee",
      "condition": "Незначительные повреждения/грязь",
      "endDate": "08.05.2025 22:15",
      "timeRemaining": "Осталось: 22 ч. 11 мин."
    },
    {
      "title": "GrassRoots G-FR-58B フォレスト スタンダード モデル エレキ ベース 4弦 グラスルーツ 中古 O9956112",
      "price": "14,300 иена(иен) (US$104,82)",
      "image": "https://cdn.buyee.jp/images/common/spacer.gif",
      "url": "https://buyee.jp/item/jdirectitems/auction/s1183613521",
      "source": "buyee",
      "condition": "Незначительные повреждения/грязь",
      "endDate": "08.05.2025 22:11",
      "timeRemaining": "Осталось: 22 ч. 6 мин."
    },
    {
      "title": "SELDER ST-16 セルダー ストラトキャスター イエロー エレキギター 楽器 中古 T9872517",
      "price": "33,000 иена(иен) (US$241,89)",
      "image": "https://cdn.buyee.jp/images/common/spacer.gif",
      "url": "https://buyee.jp/item/jdirectitems/auction/q1183648986",
      "source": "buyee",
      "condition": "Незначительные повреждения/грязь",
      "endDate": "08.05.2025 10:25",
      "timeRemaining": "Осталось: 10 ч. 21 мин."
    },
    {
      "title": "DONNER standard Series エレキ ギター ストラトタイプ 中古 W9989315",
      "price": "3,300 иена(иен) (US$24,19)",
      "image": "https://cdn.buyee.jp/images/common/spacer.gif",
      "url": "https://buyee.jp/item/jdirectitems/auction/p1183635317",
      "source": "buyee",
      "condition": "Незначительные повреждения/грязь",
      "endDate": "09.05.2025 22:22",
      "timeRemaining": "Осталось: 1 дн. 22 ч. 17 мин."
    },
    {
      "title": "Fender USA Stratocaster 1978 BLACK フェンダーU.S.A.ストラト’78 エレキギター 中古 W9790720",
      "price": "242,000 иена(иен) (US$1 773,86)",
      "image": "https://cdn.buyee.jp/images/common/spacer.gif",
      "url": "https://buyee.jp/item/jdirectitems/auction/x1183571509",
      "source": "buyee",
      "condition": "Незначительные повреждения/грязь",
      "endDate": "08.05.2025 22:33",
      "timeRemaining": "Осталось: 22 ч. 29 мин."
    },
    {
      "title": "YAMAHA EZ-EG イージーギター 電子ギター 中古 W9989316",
      "price": "11,000 иена(иен) (US$80,63)",
      "image": "https://cdn.buyee.jp/images/common/spacer.gif",
      "url": "https://buyee.jp/item/jdirectitems/auction/o1183648672",
      "source": "buyee",
      "condition": "Незначительные повреждения/грязь",
      "endDate": "09.05.2025 22:45",
      "timeRemaining": "Осталось: 1 дн. 22 ч. 40 мин."
    }
  ],
  "last_updated": "2025-05-08 00:04:44",
  "total_count": 20
}